lightrft/__init__.py
lightrft-0.1.0.dist-info/licenses/LICENSE
lightrft-0.1.0.dist-info/METADATA
lightrft-0.1.0.dist-info/WHEEL
lightrft-0.1.0.dist-info/top_level.txt
lightrft-0.1.0.dist-info/RECORD
