Metadata-Version: 2.4
Name: LightRFT
Version: 0.1.0
Summary: Light, Efficient, Omni-modal & Reward-model Driven Reinforcement Fine-Tuning Framework
Home-page: https://github.com/opendilab/LightRFT
Author: LightRFT Team
Author-email: LightRFT Team <opendilab@pjlab.org.cn>
License: Apache-2.0
Project-URL: Homepage, https://github.com/opendilab/LightRFT
Project-URL: Documentation, https://github.com/opendilab/LightRFT/tree/main/docs
Project-URL: Repository, https://github.com/opendilab/LightRFT
Project-URL: Bug Reports, https://github.com/opendilab/LightRFT/issues
Keywords: reinforcement learning,RLVR,RLHF,large language models,vision-language models,reward models,omni-modal,multi-modal,PPO,GRPO,deep learning
Classifier: Development Status :: 4 - Beta
Classifier: Intended Audience :: Developers
Classifier: Intended Audience :: Science/Research
Classifier: License :: OSI Approved :: Apache Software License
Classifier: Programming Language :: Python :: 3
Classifier: Programming Language :: Python :: 3.10
Classifier: Programming Language :: Python :: 3.11
Classifier: Topic :: Scientific/Engineering :: Artificial Intelligence
Classifier: Topic :: Software Development :: Libraries :: Python Modules
Requires-Python: >=3.10
License-File: LICENSE
Requires-Dist: torch>=2.5.1
Requires-Dist: transformers==4.51.3
Requires-Dist: vllm==0.7.3
Requires-Dist: sglang==0.4.5
Requires-Dist: deepspeed>=0.15.0
Requires-Dist: accelerate
Requires-Dist: datasets
Requires-Dist: wandb
Requires-Dist: peft
Requires-Dist: easydict
Requires-Dist: decord
Requires-Dist: orjson
Requires-Dist: bitsandbytes
Requires-Dist: einops
Requires-Dist: loralib
Requires-Dist: tensorboard
Requires-Dist: tqdm
Requires-Dist: nltk
Requires-Dist: mathruler
Requires-Dist: loguru
Requires-Dist: librosa
Provides-Extra: dev
Requires-Dist: pytest; extra == "dev"
Requires-Dist: black; extra == "dev"
Requires-Dist: pylint; extra == "dev"
Requires-Dist: yapf; extra == "dev"
Provides-Extra: docs
Requires-Dist: sphinx; extra == "docs"
Requires-Dist: sphinx-rtd-theme; extra == "docs"
Requires-Dist: sphinx-autobuild; extra == "docs"
Provides-Extra: eval
Requires-Dist: latex2sympy2; extra == "eval"
Requires-Dist: timeout_decorator; extra == "eval"
Requires-Dist: word2number; extra == "eval"
Provides-Extra: flash-attn
Requires-Dist: flash-attn; extra == "flash-attn"
Dynamic: author
Dynamic: home-page
Dynamic: license-file
Dynamic: requires-python
